Counter_Up/design.v
module counter(clk,rstn,out);

    input clk,rstn;
    output reg [3:0]out;

//We build up counter 4 bit in which the the number will count and adds value with 1 so its only work on Posedge for addition 
// before implementing the logic we use always block for positive edge in which clk produce positve edge if reset no held

    always @ (posedge clk)
    begin
        if (rstn == 1'b1)
        begin
            out = 4'b0000;
        end    
        else
        begin
            out = out + 1'b1;
        end        
    end

endmodule

Counter_Up/testbench.v
module counter_tb();

//we use clk = 0, for always providing the positive edge to our design
    reg clk = 0, rstn;
    wire [3:0]out;

    counter dut(
                    .clk(clk),
                    .rstn(rstn),
                    .out(out)
    );


    initial begin
        $dumpfile("counter.vcd");
        $dumpvars(0);

    end    


//as mentioned above ,we use ~clk when our clk signal 0 comes to then the value will change and will become 1
    always 
    begin
        clk = ~clk;
        #50;

    end
// we use reset 1 for starting the reset value high and then will provide reset value 0 so that the clock will provide 1 and it will starting the counting
    initial begin
        rstn = 1'b1;
        #100;

        rstn = 1'b0;
        #1500;
        $finish;
    end


endmodule

Counter_Up/counter.vcd
$date
	Thu Apr 11 12:41:15 2024
$end
$version
	Icarus Verilog
$end
$timescale
	1s
$end
$scope module counter_tb $end
$var wire 4 ! out [3:0] $end
$var reg 1 " clk $end
$var reg 1 # rstn $end
$scope module dut $end
$var wire 1 " clk $end
$var wire 1 # rstn $end
$var reg 4 $ out [3:0] $end
$upscope $end
$upscope $end
$enddefinitions $end
$comment Show the parameter values. $end
$dumpall
$end
#0
$dumpvars
b0 $
1#
1"
b0 !
$end
#50
0"
#100
b1 !
b1 $
1"
0#
#150
0"
#200
b10 !
b10 $
1"
#250
0"
#300
b11 !
b11 $
1"
#350
0"
#400
b100 !
b100 $
1"
#450
0"
#500
b101 !
b101 $
1"
#550
0"
#600
b110 !
b110 $
1"
#650
0"
#700
b111 !
b111 $
1"
#750
0"
#800
b1000 !
b1000 $
1"
#850
0"
#900
b1001 !
b1001 $
1"
#950
0"
#1000
b1010 !
b1010 $
1"
#1050
0"
#1100
b1011 !
b1011 $
1"
#1150
0"
#1200
b1100 !
b1100 $
1"
#1250
0"
#1300
b1101 !
b1101 $
1"
#1350
0"
#1400
b1110 !
b1110 $
1"
#1450
0"
#1500
b1111 !
b1111 $
1"
#1550
0"
#1600
b0 !
b0 $
1"
